MANIFEST.in
README.md
setup.py
src/bohrium_open_sdk/__init__.py
src/bohrium_open_sdk/_utils/__init__.py
src/bohrium_open_sdk/_utils/_logs.py
src/bohrium_open_sdk/_utils/_tools.py
src/bohrium_open_sdk/_utils/_typing.py
src/bohrium_open_sdk/_utils/_utils.py
src/bohrium_open_sdk/launching/__init__.py
src/bohrium_open_sdk/launching/compat.py
src/bohrium_open_sdk/launching/cli/__init__.py
src/bohrium_open_sdk/launching/cli/api/__init__.py
src/bohrium_open_sdk/launching/cli/api/model.py
src/bohrium_open_sdk/launching/cli/api/persistent_service.py
src/bohrium_open_sdk/launching/cli/commands/__init__.py
src/bohrium_open_sdk/launching/cli/commands/launching.py
src/bohrium_open_sdk/launching/cli/utils/__init__.py
src/bohrium_open_sdk/launching/cli/utils/random.py
src/bohrium_open_sdk/launching/report/__init__.py
src/bohrium_open_sdk/launching/typing/__init__.py
src/bohrium_open_sdk/launching/typing/basic.py
src/bohrium_open_sdk/launching/typing/benchmark.py
src/bohrium_open_sdk/launching/typing/bio.py
src/bohrium_open_sdk/launching/typing/bohrium.py
src/bohrium_open_sdk/launching/typing/dataset.py
src/bohrium_open_sdk/launching/typing/dflow.py
src/bohrium_open_sdk/launching/typing/io.py
src/bohrium_open_sdk/launching/typing/addon/__init__.py
src/bohrium_open_sdk/launching/typing/addon/sysmbol.py
src/bohrium_open_sdk/launching/typing/addon/ui.py
src/bohrium_open_sdk/opensdk/__init__.py
src/bohrium_open_sdk/opensdk/_base_client.py
src/bohrium_open_sdk/opensdk/_client.py
src/bohrium_open_sdk/opensdk/_constants.py
src/bohrium_open_sdk/opensdk/_exceptions.py
src/bohrium_open_sdk/opensdk/_resource.py
src/bohrium_open_sdk/opensdk/_response.py
src/bohrium_open_sdk/opensdk/_tiefblue_client.py
src/bohrium_open_sdk/opensdk/_types.py
src/bohrium_open_sdk/opensdk/_version.py
src/bohrium_open_sdk/opensdk/resources/__init__.py
src/bohrium_open_sdk/opensdk/resources/app/__init__.py
src/bohrium_open_sdk/opensdk/resources/app/app.py
src/bohrium_open_sdk/opensdk/resources/app/app_job.py
src/bohrium_open_sdk_qa.egg-info/PKG-INFO
src/bohrium_open_sdk_qa.egg-info/SOURCES.txt
src/bohrium_open_sdk_qa.egg-info/dependency_links.txt
src/bohrium_open_sdk_qa.egg-info/requires.txt
src/bohrium_open_sdk_qa.egg-info/top_level.txt